ukmdb_uuid/__init__.py
ukmdb_uuid/uuid.py
ukmdb_uuid-0.0.2.dist-info/DESCRIPTION.rst
ukmdb_uuid-0.0.2.dist-info/METADATA
ukmdb_uuid-0.0.2.dist-info/RECORD
ukmdb_uuid-0.0.2.dist-info/WHEEL
ukmdb_uuid-0.0.2.dist-info/metadata.json
ukmdb_uuid-0.0.2.dist-info/top_level.txt
